mrpyconvert/__init__.py
mrpyconvert/dicom_sorter.py
mrpyconvert/mrpyconvert.py
mrpyconvert-0.1.31.dist-info/LICENSE
mrpyconvert-0.1.31.dist-info/METADATA
mrpyconvert-0.1.31.dist-info/WHEEL
mrpyconvert-0.1.31.dist-info/RECORD
